minke/__init__.py
minke/windowmanager.py
minke_wm-0.1.data/scripts/minke_wm
minke_wm-0.1.dist-info/METADATA
minke_wm-0.1.dist-info/WHEEL
minke_wm-0.1.dist-info/top_level.txt
minke_wm-0.1.dist-info/RECORD
